{
	"info": {
		"_postman_id": "c0661ef7-b24e-4d2a-9410-4ec8e7e866a3",
		"name": "todoList",
		"schema": "https://schema.getpostman.com/json/collection/v2.1.0/collection.json",
		"_exporter_id": "33189110"
	},
	"item": [
		{
			"name": "取得所有代辦",
			"request": {
				"method": "GET",
				"header": [],
				"url": {
					"raw": "https://todo-nodo2024.onrender.com",
					"protocol": "https",
					"host": [
						"todo-nodo2024",
						"onrender",
						"com"
					]
				}
			},
			"response": []
		},
		{
			"name": "新增一筆代辦",
			"request": {
				"method": "POST",
				"header": [],
				"body": {
					"mode": "raw",
					"raw": "{\n    \"title\": \"小花要上課3\"\n}",
					"options": {
						"raw": {
							"language": "json"
						}
					}
				},
				"url": {
					"raw": "https://todo-nodo2024.onrender.com/todos",
					"protocol": "https",
					"host": [
						"todo-nodo2024",
						"onrender",
						"com"
					],
					"path": [
						"todos"
					]
				}
			},
			"response": []
		},
		{
			"name": "刪除一筆代辦",
			"request": {
				"method": "DELETE",
				"header": [],
				"url": {
					"raw": "https://todo-nodo2024.onrender.com/todos/265fd87f-7f3d-4d8c-820f-1b6a3b104fac",
					"protocol": "https",
					"host": [
						"todo-nodo2024",
						"onrender",
						"com"
					],
					"path": [
						"todos",
						"265fd87f-7f3d-4d8c-820f-1b6a3b104fac"
					]
				}
			},
			"response": []
		},
		{
			"name": "刪除所有代辦",
			"request": {
				"method": "DELETE",
				"header": [],
				"url": {
					"raw": "https://todo-nodo2024.onrender.com/todos",
					"protocol": "https",
					"host": [
						"todo-nodo2024",
						"onrender",
						"com"
					],
					"path": [
						"todos"
					]
				}
			},
			"response": []
		},
		{
			"name": "修改一筆代辦",
			"request": {
				"method": "PATCH",
				"header": [],
				"body": {
					"mode": "raw",
					"raw": "{\n    \"title\":\"我要修改一筆資料\"\n}",
					"options": {
						"raw": {
							"language": "json"
						}
					}
				},
				"url": {
					"raw": "https://todo-nodo2024.onrender.com/todos/88feedd7-6959-41f0-9964-4bc590ce5919",
					"protocol": "https",
					"host": [
						"todo-nodo2024",
						"onrender",
						"com"
					],
					"path": [
						"todos",
						"88feedd7-6959-41f0-9964-4bc590ce5919"
					]
				}
			},
			"response": []
		}
	]
}